dataform_tools/__init__.py
dataform_tools/dataform_tools.py
dataform_tools-1.0.7.dist-info/METADATA
dataform_tools-1.0.7.dist-info/WHEEL
dataform_tools-1.0.7.dist-info/top_level.txt
dataform_tools-1.0.7.dist-info/RECORD
