Metadata-Version: 2.4
Name: dataform-tools
Version: 1.0.7
Summary: wrapper of the Google Cloud Dataform API (google-cloud-dataform) that simplifies common operations such as listing repositories, managing workspaces, creating compilation results, and triggering workflow invocations.
Author-email: Ashish Alex <ashish.alex10@gmail.com>
License-Expression: MIT
Project-URL: Homepage, https://github.com/ashish10alex/vscode-dataform-tools/tree/main/packages/pypi
Project-URL: Bug Tracker, https://github.com/ashish10alex/vscode-dataform-tools/issues
Project-URL: Repository, https://github.com/ashish10alex/vscode-dataform-tools
Keywords: dataform,gcp,google-cloud,etl
Classifier: Programming Language :: Python
Classifier: Programming Language :: Python :: 3
Classifier: Programming Language :: Python :: 3 :: Only
Classifier: Programming Language :: Python :: 3.10
Classifier: Programming Language :: Python :: 3.11
Classifier: Programming Language :: Python :: 3.12
Classifier: Programming Language :: Python :: 3.13
Requires-Python: >=3.10
Requires-Dist: google-cloud-dataform>=0.7.0
